Tarea 1/SB1/src/design/module_decoder.sv
module decoder (input logic ag, bg, cg, dg, output logic ab, bb, cb, db);
    assign ab = ag;
    assign bb = (ag ^ bg);
    assign cb = ((ag ^ bg) ^ cg);
    assign db = (((ag ^ bg) ^ cg) ^ dg);
endmodule

module integrar_module (
    input logic ag, 
    input logic bg, 
    input logic cg, 
    input logic dg,
    output logic[3:0] led
);

    
    logic[3:0] binario;

    
    decoder decodificador (
        .ag(ag),
        .bg(bg),
        .cg(cg),
        .dg(dg),
        .ab(binario[0]),
        .bb(binario[1]),
        .cb(binario[2]),
        .db(binario[3])
    );

    
    module_leds Leds (
        .binario(binario),
        .led(led)
    );

endmodule

module module_leds (

    input logic[3:0] binario,
    output reg[3:0] led
) ;


 assign led[0] = (binario == 4'b0001)| (binario == 4'b0011)| (binario == 4'b0101) | (binario == 4'b0111) 
| (binario == 4'b1001)| (binario == 4'b1011) | (binario == 4'b1101) | (binario == 4'b1111) ; 


  assign led[1] =  (binario == 4'b0010) | (binario == 4'b0011) | (binario == 4'b0110) 
| (binario == 4'b0111) | (binario == 4'b1010) | (binario == 4'b1011) | (binario == 4'b1110) 
| (binario == 4'b1111) ;

  assign led[2] = (binario== 4'b0100)| (binario == 4'b0101) | (binario == 4'b0111) 
| (binario == 4'b0110)| (binario == 4'b1100)| (binario == 4'b1101) | (binario == 4'b1111) 
| (binario == 4'b1110) ;

 assign led[3] = (binario== 4'b1000)| (binario == 4'b1101) | (binario == 4'b1001) 
| (binario == 4'b1010)| (binario == 4'b1011)| (binario == 4'b1100) | (binario == 4'b1101) 
| (binario == 4'b1110) | (binario == 4'b1111) ;
 

endmodule

// Subsistema 3 de la tarea 1, este modulo tiene la funcionalidad de recibir los datos del subsistema 2 y desplegarlos en los dispositivos de 7 segmentos.

module module_seg (

    // Reloj para que cuando los valores del binario se actualicen se ven reflejados de forma automatica en los 7 segmentos.
    input logic clk,
    // El boton de reinicio que permite restablecer los valores de los 7 segmentos.
    input logic rst,
    // Variables de entrada las cuales vienen del subsistema 2.
    input logic A, B, C, D,
    // Estas variables de salida representan a cada uno de los segmentos que se encontraran conectados a uno de los pines de la FPGA, ademas de que sera el 7 segmentos que representa las unidades.
    output logic au, bu, cu, du, eu, fu, gu,
    // Estas variables de salida representan a cada uno de los segmentos que se encontraran conectados a uno de los pines de la FPGA, ademas de que sera el 7 segmentos que representa las decimas.
    output logic ad, bd, cd, dd, ed, fd, gd
);

    always @(posedge clk or posedge rst) begin

        if (rst) begin

            // Reiniciando los valores del 7 segmentos de unidades
            au <= 1;
            bu <= 1;
            cu <= 1; 
            du <= 1;
            eu <= 1;
            fu <= 1;
            gu <= 0;

            // Reiniciando los valores del 7 segmentos de decimas
            ad <= 1;
            bd <= 1;
            cd <= 1; 
            dd <= 1;
            ed <= 1;
            fd <= 1;
            gd <= 0;

        end else begin

            // Asignacion del 7 segmentos de unidades
            au <= (~A & ~B & ~C & ~D) | (~A & ~B & C & ~D) | (~A & ~B & C & D) | (~A & B & ~C & D) | (~A & B & C & ~D) | (~A & B & C & D) | (A & ~B & ~C & ~D) | (A & ~B & ~C & D) | (A & ~B & C & ~D) | (A & B & ~C & ~D) | (A & B & ~C & D) | (A & B & C & D);
            bu <= (~A & ~B & ~C & ~D) | (~A & ~B & ~C & D) | (~A & ~B & C & ~D) | (~A & ~B & C & D) | (~A & B & ~C & ~D) | (~A & B & C & D) | (A & ~B & ~C & ~D) | (A & ~B & ~C & D) | (A & ~B & C & ~D) | (A & ~B & C & D) | (A & B & ~C & ~D) | (A & B & ~C & D) | (A & B & C & ~D);
            cu <= (~A & ~B & ~C & ~D) | (~A & ~B & ~C & D) | (~A & ~B & C & D) | (~A & B & ~C & ~D) | (~A & B & ~C & D) | (~A & B & C & ~D) | (~A & B & C & D) | (A & ~B & ~C & ~D) | (A & ~B & ~C & D) | (A & ~B & C & ~D) | (A & ~B & C & D) | (A & B & ~C & D) | (A & B & C & ~D) | (A & B & C & D);
            du <= (~A & ~B & ~C & ~D) | (~A & ~B & C & ~D) | (~A & ~B & C & D) | (~A & B & ~C & D) | (~A & B & C & ~D) | (A & ~B & ~C & ~D) | (A & ~B & ~C & D) | (A & ~B & C & ~D) | (A & B & ~C & ~D) | (A & B & ~C & D) | (A & B & C & D);
            eu <= (~A & ~B & ~C & ~D) | (~A & ~B & C & ~D) | (~A & B & C & ~D) | (A & ~B & ~C & ~D) | (A & ~B & C & ~D) | (A & B & ~C & ~D);
            fu <= (~A & ~B & ~C & ~D) | (~A & B & ~C & ~D) | (~A & B & ~C & D) | (~A & B & C & ~D) | (A & ~B & ~C & ~D) | (A & ~B & ~C & D) | (A & ~B & C & ~D) | (A & B & C & ~D) | (A & B & C & D);
            gu <= (~A & ~B & C & ~D) | (~A & ~B & C & D) | (~A & B & ~C & ~D) | (~A & B & ~C & D) | (~A & B & C & ~D) | (A & ~B & ~C & ~D) | (A & ~B & ~C & D) | (A & B & ~C & ~D) | (A & B & ~C & D) | (A & B & C & ~D) | (A & B & C & D);

            // Asignacion del 7 segmentos de decimas
            ad <= (~A & ~B & ~C & ~D) | (~A & ~B & ~C & D) | (~A & ~B & C & ~D) | (~A & ~B & C & D) | (~A & B & ~C & ~D) | (~A & B & ~C & D) | (~A & B & C & ~D) | (~A & B & C & D) | (A & ~B & ~C & ~D) | (A & ~B & ~C & D);
            bd <= 1; // El segmento b del 7 segmentos de decimas en este proyecto siempre esta encendido.
            cd <= 1; // El segmento c del 7 segmentos de decimas en este proyecto siempre esta encendido.
            dd <= (~A & ~B & ~C & ~D) | (~A & ~B & ~C & D) | (~A & ~B & C & ~D) | (~A & ~B & C & D) | (~A & B & ~C & ~D) | (~A & B & ~C & D) | (~A & B & C & ~D) | (~A & B & C & D) | (A & ~B & ~C & ~D) | (A & ~B & ~C & D);
            ed <= (~A & ~B & ~C & ~D) | (~A & ~B & ~C & D) | (~A & ~B & C & ~D) | (~A & ~B & C & D) | (~A & B & ~C & ~D) | (~A & B & ~C & D) | (~A & B & C & ~D) | (~A & B & C & D) | (A & ~B & ~C & ~D) | (A & ~B & ~C & D);
            fd <= (~A & ~B & ~C & ~D) | (~A & ~B & ~C & D) | (~A & ~B & C & ~D) | (~A & ~B & C & D) | (~A & B & ~C & ~D) | (~A & B & ~C & D) | (~A & B & C & ~D) | (~A & B & C & D) | (A & ~B & ~C & ~D) | (A & ~B & ~C & D);
            gd <= 0; // El segmento g del 7 segmentos de decimas en este proyecto siempre esta apagado.

        end

    end 

endmodule

Tarea 1/SB1/src/sim/module_decoder_tb.sv

`timescale 1ns / 1ps

module decoder_tb;

    // Inputs
    reg ag;
    reg bg;
    reg cg;
    reg dg;

    // Outputs
    wire ab;
    wire bb;
    wire cb;
    wire db;

    
    decoder dut (
        .ag(ag),
        .bg(bg),
        .cg(cg),
        .dg(dg),
        .ab(ab),
        .bb(bb),
        .cb(cb),
        .db(db)
    );



   
    initial begin
       
        ag = 0; bg = 0; cg = 0; dg = 0;

        // casos

		#10; ag = 0; bg = 0; cg = 0; dg = 0; // salida esperada: ab=0, bb=0, cb=0, db=0
        #10; ag = 1; bg = 0; cg = 0; dg = 0; // salida esperada: ab=1, bb=1, cb=1, db=1
        #10; ag = 0; bg = 1; cg = 0; dg = 0; // salida esperada: ab=0, bb=1, cb=1, db=1
        #10; ag = 1; bg = 1; cg = 0; dg = 0; // salida esperada: ab=1, bb=0, cb=1, db=1
        #10; ag = 0; bg = 0; cg = 1; dg = 0; // salida esperada: ab=0, bb=0, cb=1, db=1
        #10; ag = 1; bg = 0; cg = 1; dg = 0; // salida esperada: ab=1, bb=1, cb=0, db=1
        #10; ag = 0; bg = 1; cg = 1; dg = 0; // salida esperada: ab=0, bb=1, cb=0, db=1
        #10; ag = 1; bg = 1; cg = 1; dg = 0; // salida esperada: ab=1, bb=0, cb=1, db=1
        #10; ag = 0; bg = 0; cg = 0; dg = 1; // salida esperada: ab=0, bb=0, cb=0, db=1 
        #10; ag = 1; bg = 0; cg = 0; dg = 1; // salida esperada: ab=1, bb=1, cb=1, db=0
        #10; ag = 0; bg = 1; cg = 0; dg = 1; // salida esperada: ab=0, bb=1, cb=1, db=0
        #10; ag = 1; bg = 1; cg = 0; dg = 1; // salida esperada: ab=1, bb=0, cb=1, db=0
        #10; ag = 0; bg = 0; cg = 1; dg = 1; // salida esperada: ab=0, bb=0, cb=1, db=0 
        #10; ag = 1; bg = 0; cg = 1; dg = 1; // salida esperada: ab=1, bb=1, cb=0, db=0
        #10; ag = 0; bg = 1; cg = 1; dg = 1; // salida esperada: ab=0, bb=1, cb=0, db=0
        #10; ag = 1; bg = 1; cg = 1; dg = 1; // salida esperada: ab=1, bb=0, cb=1, db=0


        
        $finish;
    end
	
    initial begin
    $dumpfile("decoder_tb.vcd");
    $dumpvars(0,decoder_tb);
    end

endmodule

module module_leds_tb;

    logic [3:0] binario;
    logic [3:0] led;

    module_leds uut (
        .binario(binario),
        .led(led)
    );

    initial begin

        binario = 4'b0000;
        #10;
        $display(led[3], led[2], led[1], led[0]);
        binario = 4'b0001;
       #10;  
       $display(led[3], led[2], led[1], led[0]);
        binario = 4'b0010;
        #10;  
        $display(led[3], led[2], led[1], led[0]);
        binario = 4'b0011;
        #10;  
        $display(led[3], led[2], led[1], led[0]);
        binario = 4'b0100;
        #10;  
        $display(led[3], led[2], led[1], led[0]);
        binario = 4'b0101;
        #10;  
        $display(led[3], led[2], led[1], led[0]);
        binario = 4'b0110;
        #10;  
        $display(led[3], led[2], led[1], led[0]);
        binario = 4'b0111;
        #10;  
        $display(led[3], led[2], led[1], led[0]);
        binario = 4'b1000;
        #10;  
        $display(led[3], led[2], led[1], led[0]);
        binario = 4'b1001;
        #10;  
        $display(led[3], led[2], led[1], led[0]);
        binario = 4'b1010;
        #10;  
        $display(led[3], led[2], led[1], led[0]);
        binario = 4'b1011;
        #10;  
        $display(led[3], led[2], led[1], led[0]);
        binario = 4'b1100;
        #10;  
        $display(led[3], led[2], led[1], led[0]);
        binario = 4'b1101;
        #10;  
        $display(led[3], led[2], led[1], led[0]);
        binario = 4'b1110;
        #10;  
        $display(led[3], led[2], led[1], led[0]);
        binario = 4'b1111;
        #10;  
        $display(led[3], led[2], led[1], led[0]);
        

        $finish;
    end


    initial begin
        $dumpfile("module_leds_tb.vcd");
        $dumpvars(0, module_leds_tb);
    end


endmodule

module module_seg_tb;

    // Declaracion de las señales para el testbench.
    logic clk;
    logic rst;
    logic A, B, C, D;
    logic au, bu, cu, du, eu, fu, gu;
    logic ad, bd, cd, dd, ed, fd, gd;

    // Declaracion de las instancias para el testbench, unidad bajo prueba "uut".
    module_seg uut (
        .clk(clk),
        .rst(rst),
        .A(A),
        .B(B),
        .C(C),
        .D(D),
        .au(au),
        .bu(bu),
        .cu(cu),
        .du(du),
        .eu(eu),
        .fu(fu),
        .gu(gu),
        .ad(ad),
        .bd(bd),
        .cd(cd),
        .dd(dd),
        .ed(ed),
        .fd(fd),
        .gd(gd)
    );

    // Establecer el sistema del reloj, cada periodo es igual a 10 unidades de tiempo.
    always begin

        clk = 1; 
        #5;
        clk = 0;
        #5;

    end

    // Inicio de la prueba del modulo.
    initial begin

        // Valores iniciales de la prueba.
        rst = 1;
        A = 0;
        B = 0;
        C = 0;
        D = 0;

        // Cambio en el valor de rst, tras 10 unidades de tiempo.
        #10;
        rst = 0;

        // Cambio en los valores de entrada iniciales, cada 10 unidades de tiempo.
        // Primer cambio 
        #10;
        A = 0;
        B = 1;
        C = 1;
        D = 0;

        // Segundo cambio
        #10;
        A = 1;
        B = 0;
        C = 1;
        D = 0;

        // Tercer cambio
        #10;
        A = 1;
        B = 1;
        C = 0;
        D = 0;

        // Finalizacion de la prueba
        #10;
        $finish;
        
    end

    // Sistema de guardado de los resultados del testbench.
    initial begin

        $dumpfile("module_seg_tb.vcd");
        $dumpvars(0,module_seg_tb);

    end 

endmodule

Tarea 1/SB1/src/build/decoder_tb.vcd
$date
	Fri Aug 23 12:23:28 2024
$end
$version
	Icarus Verilog
$end
$timescale
	1ps
$end
$scope module decoder_tb $end
$var wire 1 ! db $end
$var wire 1 " cb $end
$var wire 1 # bb $end
$var wire 1 $ ab $end
$var reg 1 % ag $end
$var reg 1 & bg $end
$var reg 1 ' cg $end
$var reg 1 ( dg $end
$scope module dut $end
$var wire 1 $ ab $end
$var wire 1 % ag $end
$var wire 1 # bb $end
$var wire 1 & bg $end
$var wire 1 " cb $end
$var wire 1 ' cg $end
$var wire 1 ! db $end
$var wire 1 ( dg $end
$upscope $end
$upscope $end
$enddefinitions $end
$comment Show the parameter values. $end
$dumpall
$end
#0
$dumpvars
0(
0'
0&
0%
0$
0#
0"
0!
$end
#20000
1!
1"
1#
1$
1%
#30000
1&
0$
0%
#40000
0!
0"
0#
1$
1%
#50000
1!
1"
1'
0&
0$
0%
#60000
0!
0"
1#
1$
1%
#70000
1&
0$
0%
#80000
1!
1"
0#
1$
1%
#90000
0"
1(
0'
0&
0$
0%
#100000
0!
1"
1#
1$
1%
#110000
1&
0$
0%
#120000
1!
0"
0#
1$
1%
#130000
0!
1"
1'
0&
0$
0%
#140000
1!
0"
1#
1$
1%
#150000
1&
0$
0%
#160000
0!
1"
0#
1$
1%
