Tarea 1/SB1/src/design/module_decoder.sv
module decoder (input logic ag, bg, cg, dg, output logic ab, bb, cb, db);
    assign ab = ag;
    assign bb = (ag ^ bg);
    assign cb = ((ag ^ bg) ^ cg);
    assign db = (((ag ^ bg) ^ cg) ^ dg);
endmodule

Tarea 1/SB1/src/sim/module_decoder_tb.sv

`timescale 1ns / 1ps

module decoder_tb;

    // Inputs
    reg ag;
    reg bg;
    reg cg;
    reg dg;

    // Outputs
    wire ab;
    wire bb;
    wire cb;
    wire db;

    
    decoder dut (
        .ag(ag),
        .bg(bg),
        .cg(cg),
        .dg(dg),
        .ab(ab),
        .bb(bb),
        .cb(cb),
        .db(db)
    );



   
    initial begin
       
        ag = 0; bg = 0; cg = 0; dg = 0;

        // casos

		#10; ag = 0; bg = 0; cg = 0; dg = 0; // salida esperada: ab=0, bb=0, cb=0, db=0
        #10; ag = 1; bg = 0; cg = 0; dg = 0; // salida esperada: ab=1, bb=1, cb=1, db=1
        #10; ag = 0; bg = 1; cg = 0; dg = 0; // salida esperada: ab=0, bb=1, cb=1, db=1
        #10; ag = 1; bg = 1; cg = 0; dg = 0; // salida esperada: ab=1, bb=0, cb=1, db=1
        #10; ag = 0; bg = 0; cg = 1; dg = 0; // salida esperada: ab=0, bb=0, cb=1, db=1
        #10; ag = 1; bg = 0; cg = 1; dg = 0; // salida esperada: ab=1, bb=1, cb=0, db=1
        #10; ag = 0; bg = 1; cg = 1; dg = 0; // salida esperada: ab=0, bb=1, cb=0, db=1
        #10; ag = 1; bg = 1; cg = 1; dg = 0; // salida esperada: ab=1, bb=0, cb=1, db=1
        #10; ag = 0; bg = 0; cg = 0; dg = 1; // salida esperada: ab=0, bb=0, cb=0, db=1 
        #10; ag = 1; bg = 0; cg = 0; dg = 1; // salida esperada: ab=1, bb=1, cb=1, db=0
        #10; ag = 0; bg = 1; cg = 0; dg = 1; // salida esperada: ab=0, bb=1, cb=1, db=0
        #10; ag = 1; bg = 1; cg = 0; dg = 1; // salida esperada: ab=1, bb=0, cb=1, db=0
        #10; ag = 0; bg = 0; cg = 1; dg = 1; // salida esperada: ab=0, bb=0, cb=1, db=0 
        #10; ag = 1; bg = 0; cg = 1; dg = 1; // salida esperada: ab=1, bb=1, cb=0, db=0
        #10; ag = 0; bg = 1; cg = 1; dg = 1; // salida esperada: ab=0, bb=1, cb=0, db=0
        #10; ag = 1; bg = 1; cg = 1; dg = 1; // salida esperada: ab=1, bb=0, cb=1, db=0


        
        $finish;
    end
	
    initial begin
    $dumpfile("decoder_tb.vcd");
    $dumpvars(0,decoder_tb);
    end

endmodule

Tarea 1/SB1/src/build/decoder_tb.vcd
$date
	Thu Aug 22 20:20:24 2024
$end
$version
	Icarus Verilog
$end
$timescale
	1ps
$end
$scope module decoder_tb $end
$var wire 1 ! db $end
$var wire 1 " cb $end
$var wire 1 # bb $end
$var wire 1 $ ab $end
$var reg 1 % ag $end
$var reg 1 & bg $end
$var reg 1 ' cg $end
$var reg 1 ( dg $end
$scope module dut $end
$var wire 1 $ ab $end
$var wire 1 % ag $end
$var wire 1 # bb $end
$var wire 1 & bg $end
$var wire 1 " cb $end
$var wire 1 ' cg $end
$var wire 1 ! db $end
$var wire 1 ( dg $end
$upscope $end
$upscope $end
$enddefinitions $end
$comment Show the parameter values. $end
$dumpall
$end
#0
$dumpvars
0(
0'
0&
0%
0$
0#
0"
0!
$end
#20000
1!
1"
1#
1$
1%
#30000
1&
0$
0%
#40000
0!
0"
0#
1$
1%
#50000
1!
1"
1'
0&
0$
0%
#60000
0!
0"
1#
1$
1%
#70000
1&
0$
0%
#80000
1!
1"
0#
1$
1%
#90000
0"
1(
0'
0&
0$
0%
#100000
0!
1"
1#
1$
1%
#110000
1&
0$
0%
#120000
1!
0"
0#
1$
1%
#130000
0!
1"
1'
0&
0$
0%
#140000
1!
0"
1#
1$
1%
#150000
1&
0$
0%
#160000
0!
1"
0#
1$
1%
