Tarea 1/Proyecto_1/src/design/module_seg.sv
// Subsistema 3 de la tarea 1, este modulo tiene la funcionalidad de recibir los datos del subsistema 1 y desplegarlos en los dispositivos de 7 segmentos.

module module_seg (

    // Reloj para que cuando los valores del binario se actualicen se ven reflejados de forma automatica en los 7 segmentos.
    input logic clk,
    // Variables de entrada las cuales vienen del module_decoder ya en tipo binario.
    input logic A, B, C, D,
    // Estas variables de salida representan a cada uno de los segmentos que se encontraran conectados a uno de los pines de la FPGA, ademas de que sera el 7 segmentos que representa las unidades.
    output logic au, bu, cu, du, eu, fu, gu,
    // Estas variables de salida representan a cada uno de los segmentos que se encontraran conectados a uno de los pines de la FPGA, ademas de que sera el 7 segmentos que representa las decimas.
    output logic ad, bd, cd, dd, ed, fd, gd 
    );

    always @(posedge clk) begin

        // Asignacion del 7 segmentos de unidades
        au <= ~((~A & ~B & ~C & ~D) | (~A & ~B & C & ~D) | (~A & ~B & C & D) | (~A & B & ~C & D) | (~A & B & C & ~D) | (~A & B & C & D) | (A & ~B & ~C & ~D) | (A & ~B & ~C & D) | (A & ~B & C & ~D) | (A & B & ~C & ~D) | (A & B & ~C & D) | (A & B & C & D));
        bu <= ~((~A & ~B & ~C & ~D) | (~A & ~B & ~C & D) | (~A & ~B & C & ~D) | (~A & ~B & C & D) | (~A & B & ~C & ~D) | (~A & B & C & D) | (A & ~B & ~C & ~D) | (A & ~B & ~C & D) | (A & ~B & C & ~D) | (A & ~B & C & D) | (A & B & ~C & ~D) | (A & B & ~C & D) | (A & B & C & ~D));
        cu <= ~((~A & ~B & ~C & ~D) | (~A & ~B & ~C & D) | (~A & ~B & C & D) | (~A & B & ~C & ~D) | (~A & B & ~C & D) | (~A & B & C & ~D) | (~A & B & C & D) | (A & ~B & ~C & ~D) | (A & ~B & ~C & D) | (A & ~B & C & ~D) | (A & ~B & C & D) | (A & B & ~C & D) | (A & B & C & ~D) | (A & B & C & D));
        du <= ~((~A & ~B & ~C & ~D) | (~A & ~B & C & ~D) | (~A & ~B & C & D) | (~A & B & ~C & D) | (~A & B & C & ~D) | (A & ~B & ~C & ~D) | (A & ~B & ~C & D) | (A & ~B & C & ~D) | (A & B & ~C & ~D) | (A & B & ~C & D) | (A & B & C & D));
        eu <= ~((~A & ~B & ~C & ~D) | (~A & ~B & C & ~D) | (~A & B & C & ~D) | (A & ~B & ~C & ~D) | (A & ~B & C & ~D) | (A & B & ~C & ~D));
        fu <= ~((~A & ~B & ~C & ~D) | (~A & B & ~C & ~D) | (~A & B & ~C & D) | (~A & B & C & ~D) | (A & ~B & ~C & ~D) | (A & ~B & ~C & D) | (A & ~B & C & ~D) | (A & B & C & ~D) | (A & B & C & D));
        gu <= ~((~A & ~B & C & ~D) | (~A & ~B & C & D) | (~A & B & ~C & ~D) | (~A & B & ~C & D) | (~A & B & C & ~D) | (A & ~B & ~C & ~D) | (A & ~B & ~C & D) | (A & B & ~C & ~D) | (A & B & ~C & D) | (A & B & C & ~D) | (A & B & C & D));

        // Asignacion del 7 segmentos de decimas
        ad <= ~((~A & ~B & ~C & ~D) | (~A & ~B & ~C & D) | (~A & ~B & C & ~D) | (~A & ~B & C & D) | (~A & B & ~C & ~D) | (~A & B & ~C & D) | (~A & B & C & ~D) | (~A & B & C & D) | (A & ~B & ~C & ~D) | (A & ~B & ~C & D));
        bd <= 0; // El segmento b del 7 segmentos de decimas en este proyecto siempre esta encendido.
        cd <= 0; // El segmento c del 7 segmentos de decimas en este proyecto siempre esta encendido.
        dd <= ~((~A & ~B & ~C & ~D) | (~A & ~B & ~C & D) | (~A & ~B & C & ~D) | (~A & ~B & C & D) | (~A & B & ~C & ~D) | (~A & B & ~C & D) | (~A & B & C & ~D) | (~A & B & C & D) | (A & ~B & ~C & ~D) | (A & ~B & ~C & D));
        ed <= ~((~A & ~B & ~C & ~D) | (~A & ~B & ~C & D) | (~A & ~B & C & ~D) | (~A & ~B & C & D) | (~A & B & ~C & ~D) | (~A & B & ~C & D) | (~A & B & C & ~D) | (~A & B & C & D) | (A & ~B & ~C & ~D) | (A & ~B & ~C & D));
        fd <= ~((~A & ~B & ~C & ~D) | (~A & ~B & ~C & D) | (~A & ~B & C & ~D) | (~A & ~B & C & D) | (~A & B & ~C & ~D) | (~A & B & ~C & D) | (~A & B & C & ~D) | (~A & B & C & D) | (A & ~B & ~C & ~D) | (A & ~B & ~C & D));
        gd <= 1; // El segmento g del 7 segmentos de decimas en este proyecto siempre esta apagado.

    end 

endmodule

Tarea 1/Proyecto_1/src/design/module_leds.sv
// Este modulo se hace cargo de agarrar los datos procedentes del module_decoder y presentarlos en 4 leds
module module_leds (
    // Valores de entrada provenientes de la salida del module_decoder
    input logic[3:0] binario,
    // Valores de salida a los leds de la FPGA
    output reg[3:0] led
    );

    assign led[0] = ~((binario == 4'b0001)| (binario == 4'b0011)| (binario == 4'b0101) | (binario == 4'b0111) | (binario == 4'b1001)| (binario == 4'b1011) | (binario == 4'b1101) | (binario == 4'b1111)) ; 

    assign led[1] = ~((binario == 4'b0010) | (binario == 4'b0011) | (binario == 4'b0110) | (binario == 4'b0111) | (binario == 4'b1010) | (binario == 4'b1011) | (binario == 4'b1110) | (binario == 4'b1111)) ;

    assign led[2] = ~((binario== 4'b0100)| (binario == 4'b0101) | (binario == 4'b0111) | (binario == 4'b0110)| (binario == 4'b1100)| (binario == 4'b1101) | (binario == 4'b1111) | (binario == 4'b1110)) ;

    assign led[3] = ~((binario== 4'b1000)| (binario == 4'b1101) | (binario == 4'b1001) | (binario == 4'b1010)| (binario == 4'b1011)| (binario == 4'b1100) | (binario == 4'b1101) | (binario == 4'b1110) | (binario == 4'b1111));
 
endmodule

Tarea 1/Proyecto_1/src/design/module_decoder.sv
// Este modulo recibe una señal externa y la decodifica de codigo gray a binario
module decoder (
    // valores de entrada provenientes de un switch en codigo de gray
    input logic ag, bg, cg, dg, 
    // Valores de salida en codigo binario
    output logic ab, bb, cb, db);
    assign ab = ag;
    assign bb = (ag ^ bg);
    assign cb = ((ag ^ bg) ^ cg);
    assign db = (((ag ^ bg) ^ cg) ^ dg);
endmodule

Tarea 1/Proyecto_1/src/design/module_top_2.sv
module top_module_2 (
    input logic clk,
    input logic ag, bg, cg, dg, 
    output logic [3:0] led,
    output logic au, bu, cu, du, eu, fu, gu, 
    output logic ad, bd, cd, dd, ed, fd, gd  
);

    logic ab, bb, cb, db;
    logic [3:0] binario;

    decoder u_decoder (
        .ag(ag),
        .bg(bg),
        .cg(cg),
        .dg(dg),
        .ab(ab),
        .bb(bb),
        .cb(cb),
        .db(db)
    );

    assign binario = {ab, bb, cb, db};

    module_leds u_module_leds (
        .binario(binario),
        .led(led)
    );

    module_seg u_module_seg (
        .clk(clk),
        .A(ab),
        .B(bb),
        .C(cb),
        .D(db),
        .au(au),
        .bu(bu),
        .cu(cu),
        .du(du),
        .eu(eu),
        .fu(fu),
        .gu(gu),
        .ad(ad),
        .bd(bd),
        .cd(cd),
        .dd(dd),
        .ed(ed),
        .fd(fd),
        .gd(gd)
    );

endmodule

Tarea 1/Proyecto_1/src/sim/module_top_tb.sv
module top_module_tb;

    logic clk;
    logic ag, bg, cg, dg;
    logic [3:0] led;
    logic au, bu, cu, du, eu, fu, gu;
    logic ad, bd, cd, dd, ed, fd, gd;

    top_module_2 dut (
        .clk(clk),
        .ag(ag),
        .bg(bg),
        .cg(cg),
        .dg(dg),
        .led(led),
        .au(au),
        .bu(bu),
        .cu(cu),
        .du(du),
        .eu(eu),
        .fu(fu),
        .gu(gu),
        .ad(ad),
        .bd(bd),
        .cd(cd),
        .dd(dd),
        .ed(ed),
        .fd(fd),
        .gd(gd)
    );

    initial begin
        clk = 0;
        forever #5 clk = ~clk;
    end

    initial begin
        ag = 0;
        bg = 0;
        cg = 0;
        dg = 0;
        #20;
        
        ag = 1; bg = 0; cg = 0; dg = 0;
        #5;
        ag = 0; bg = 1; cg = 0; dg = 0;
        #5;
        ag = 0; bg = 0; cg = 1; dg = 0;
        #5;
        ag = 0; bg = 0; cg = 0; dg = 1;
        #5;
        
        ag = 1; bg = 1; cg = 0; dg = 0;
        #5;
        ag = 1; bg = 1; cg = 1; dg = 0;
        #5;
        ag = 1; bg = 1; cg = 1; dg = 1;
        #5;
        ag = 0; bg = 0; cg = 0; dg = 0; 
        #5;

        $finish;
    end

    initial begin
        $monitor("Time = %0t | led = %b | au = %b, bu = %b, cu = %b, du = %b, eu = %b, fu = %b, gu = %b",
        $time, led, au, bu, cu, du, eu, fu, gu);


    end

endmodule

Tarea 1/Proyecto_1/src/build/module_top_tb.vcd
$date
	Thu Aug 29 15:38:23 2024
$end
$version
	Icarus Verilog
$end
$timescale
	1s
$end
$scope module top_module_tb $end
$var wire 4 ! led [3:0] $end
$var wire 1 " gu $end
$var wire 1 # gd $end
$var wire 1 $ fu $end
$var wire 1 % fd $end
$var wire 1 & eu $end
$var wire 1 ' ed $end
$var wire 1 ( du $end
$var wire 1 ) dd $end
$var wire 1 * cu $end
$var wire 1 + cd $end
$var wire 1 , bu $end
$var wire 1 - bd $end
$var wire 1 . au $end
$var wire 1 / ad $end
$var reg 1 0 ag $end
$var reg 1 1 bg $end
$var reg 1 2 cg $end
$var reg 1 3 clk $end
$var reg 1 4 dg $end
$scope module dut $end
$var wire 1 0 ag $end
$var wire 1 1 bg $end
$var wire 1 2 cg $end
$var wire 1 3 clk $end
$var wire 1 4 dg $end
$var wire 4 5 led [3:0] $end
$var wire 1 " gu $end
$var wire 1 # gd $end
$var wire 1 $ fu $end
$var wire 1 % fd $end
$var wire 1 & eu $end
$var wire 1 ' ed $end
$var wire 1 ( du $end
$var wire 1 ) dd $end
$var wire 1 6 db $end
$var wire 1 * cu $end
$var wire 1 + cd $end
$var wire 1 7 cb $end
$var wire 1 , bu $end
$var wire 4 8 binario [3:0] $end
$var wire 1 - bd $end
$var wire 1 9 bb $end
$var wire 1 . au $end
$var wire 1 / ad $end
$var wire 1 : ab $end
$scope module u_decoder $end
$var wire 1 : ab $end
$var wire 1 0 ag $end
$var wire 1 9 bb $end
$var wire 1 1 bg $end
$var wire 1 7 cb $end
$var wire 1 2 cg $end
$var wire 1 6 db $end
$var wire 1 4 dg $end
$upscope $end
$scope module u_module_leds $end
$var wire 4 ; binario [3:0] $end
$var wire 4 < led [3:0] $end
$upscope $end
$scope module u_module_seg $end
$var wire 1 : A $end
$var wire 1 9 B $end
$var wire 1 7 C $end
$var wire 1 6 D $end
$var wire 1 3 clk $end
$var reg 1 / ad $end
$var reg 1 . au $end
$var reg 1 - bd $end
$var reg 1 , bu $end
$var reg 1 + cd $end
$var reg 1 * cu $end
$var reg 1 ) dd $end
$var reg 1 ( du $end
$var reg 1 ' ed $end
$var reg 1 & eu $end
$var reg 1 % fd $end
$var reg 1 $ fu $end
$var reg 1 # gd $end
$var reg 1 " gu $end
$upscope $end
$upscope $end
$upscope $end
$enddefinitions $end
$comment Show the parameter values. $end
$dumpall
$end
#0
$dumpvars
b1111 <
b0 ;
0:
09
b0 8
07
06
b1111 5
04
03
02
01
00
x/
x.
x-
x,
x+
x*
x)
x(
x'
x&
x%
x$
x#
x"
b1111 !
$end
#5
0#
1%
1'
1)
1+
1-
1/
0"
1$
1&
1(
1*
1,
1.
13
#10
03
#15
13
#20
b0 !
b0 5
b0 <
16
17
19
03
b1111 8
b1111 ;
1:
10
#25
0%
0'
0)
0/
1"
0&
0,
13
#30
03
#35
13
#40
b1000 !
b1000 5
b1000 <
03
11
b111 8
b111 ;
0:
00
#45
1%
1'
1)
1/
0"
0$
0(
1,
13
#50
03
#55
13
#60
b1100 !
b1100 5
b1100 <
b11 8
b11 ;
09
03
12
01
#65
1"
1(
13
#70
03
#75
13
#80
b1110 !
b1110 5
b1110 <
b1 8
b1 ;
07
03
14
02
#85
0"
0(
0.
13
#90
03
#95
13
#100
b111 !
b111 5
b111 <
06
03
04
11
b1000 8
b1000 ;
1:
10
#105
1"
1$
1&
1(
1.
13
#110
03
#115
13
#120
b100 !
b100 5
b100 <
16
b1011 8
b1011 ;
17
03
12
#125
0%
0'
0)
0/
0"
0$
0&
0(
0.
13
#130
03
#135
13
#140
b101 !
b101 5
b101 <
b1010 8
b1010 ;
06
03
14
#145
1$
1&
1(
1.
13
#150
03
#155
13
#160
b1111 !
b1111 5
b1111 <
07
03
04
02
01
b0 8
b0 ;
0:
00
#165
1%
1'
1)
1/
13
